soyla/__init__.py
soyla/__main__.py
soyla/audio.py
soyla/model.py
soyla/soyla.py
soyla/state.py
soyla/view.py
soyla-0.0.1.dist-info/LICENSE
soyla-0.0.1.dist-info/METADATA
soyla-0.0.1.dist-info/WHEEL
soyla-0.0.1.dist-info/top_level.txt
soyla-0.0.1.dist-info/RECORD
