Metadata-Version: 2.1
Name: soyla
Version: 0.0.1
Summary: Simple terminal program to record tts dataset
Home-page: https://github.com/bazukas/soyla
Author: Azat Khasanshin
Author-email: azatkhasanshin@gmail.com
License: UNKNOWN
Platform: UNKNOWN
Classifier: Programming Language :: Python :: 3
Classifier: License :: OSI Approved :: MIT License
Classifier: Operating System :: OS Independent
Requires-Dist: numpy
Requires-Dist: scipy
Requires-Dist: sounddevice
Requires-Dist: urwid
